README.md
setup.cfg
setup.py
outlier_remover_bhanu/__init__.py
outlier_remover_bhanu/basic.py
outlier_remover_bhanu/oremover.py
outlier_remover_bhanu.egg-info/PKG-INFO
outlier_remover_bhanu.egg-info/SOURCES.txt
outlier_remover_bhanu.egg-info/dependency_links.txt
outlier_remover_bhanu.egg-info/top_level.txt