Metadata-Version: 2.1
Name: outlier-remover-bhanu
Version: 0.0.3
Summary: Implementation of Outlier removal using row method in python.
Home-page: https://github.com/eternaldemon/outlier_remover
Author: Bhanu/eternal_demon
Author-email: aggarwal.bhanu02@gmail.com
License: UNKNOWN
Download-URL: https://github.com/eternaldemon/outlier_remover/archive/0.0.3.tar.gz
Platform: UNKNOWN
Classifier: Programming Language :: Python :: 3
Classifier: License :: OSI Approved :: MIT License
Classifier: Operating System :: OS Independent
Requires-Python: >=3.6
